{"cameraMode":{"drawMode":0,"name":"Shaded","section":"Shading Mode"},"sceneLighting":true,"audioPlay":false,"sceneViewState":{"m_AlwaysRefresh":false,"showFog":true,"showSkybox":true,"showFlares":true,"showImageEffects":true,"showParticleSystems":true,"showVisualEffectGraphs":true,"m_FxEnabled":true},"in2DMode":false,"pivot":{"x":1.3317599296569825,"y":-3.2371277809143068,"z":2.370858907699585},"rotation":{"x":0.2833044230937958,"y":0.293017715215683,"z":-0.08874998986721039,"w":0.9089367389678955},"size":8.069355010986329,"orthographic":false}