{"cameraMode":{"drawMode":0,"name":"Shaded","section":"Shading Mode"},"sceneLighting":true,"audioPlay":false,"sceneViewState":{"m_AlwaysRefresh":false,"showFog":true,"showSkybox":true,"showFlares":true,"showImageEffects":true,"showParticleSystems":true,"showVisualEffectGraphs":true,"m_FxEnabled":true},"in2DMode":false,"pivot":{"x":-2.5139048099517824,"y":3.350274085998535,"z":-8.154656410217286},"rotation":{"x":-0.28110188245773318,"y":0.40318387746810915,"z":-0.131658136844635,"w":-0.8609047532081604},"size":2.974565029144287,"orthographic":false}