{"cameraMode":{"drawMode":0,"name":"Shaded","section":"Shading Mode"},"sceneLighting":true,"audioPlay":false,"sceneViewState":{"m_AlwaysRefresh":false,"showFog":true,"showSkybox":true,"showFlares":true,"showImageEffects":true,"showParticleSystems":true,"showVisualEffectGraphs":true,"m_FxEnabled":true},"in2DMode":false,"pivot":{"x":-8.14133071899414,"y":-4.550374507904053,"z":-5.819873809814453},"rotation":{"x":-0.1391099989414215,"y":0.7536390423774719,"z":-0.16916914284229279,"w":-0.6197271347045898},"size":6.310063362121582,"orthographic":false}